mailqueue_runner-0.13.1.dist-info/licenses/LICENSE.txt
schwarz/mailqueue/__init__.py
schwarz/mailqueue/aliases_parser.py
schwarz/mailqueue/app_helpers.py
schwarz/mailqueue/compat.py
schwarz/mailqueue/maildir_utils.py
schwarz/mailqueue/mailer.py
schwarz/mailqueue/mailflow_check.py
schwarz/mailqueue/message_handler.py
schwarz/mailqueue/message_utils.py
schwarz/mailqueue/mq_mail.py
schwarz/mailqueue/mq_sendmail.py
schwarz/mailqueue/plugins.py
schwarz/mailqueue/queue_runner.py
schwarz/mailqueue/smtpclient.py
schwarz/mailqueue/testutils.py
schwarz/mailqueue/cli/__init__.py
schwarz/mailqueue/cli/mq_mail.py
schwarz/mailqueue/cli/mq_sendmail.py
schwarz/mailqueue/cli/one_shot_queue_run.py
schwarz/mailqueue/cli/send_test_message.py
schwarz/mailqueue/lib/__init__.py
schwarz/mailqueue/lib/result.py
schwarz/mailqueue/lib/smtplib_py37.py
schwarz/mailqueue/lib/tests/__init__.py
schwarz/mailqueue/lib/tests/result_test.py
mailqueue_runner-0.13.1.dist-info/METADATA
mailqueue_runner-0.13.1.dist-info/WHEEL
mailqueue_runner-0.13.1.dist-info/entry_points.txt
mailqueue_runner-0.13.1.dist-info/top_level.txt
mailqueue_runner-0.13.1.dist-info/RECORD
