Metadata-Version: 2.4
Name: mailqueue-runner
Version: 0.13.1
Home-page: https://github.com/FelixSchwarz/mailqueue-runner
Author: Felix Schwarz
Author-email: felix.schwarz@oss.schwarz.eu
License: MIT and Python
Requires-Python: >=3.6
License-File: LICENSE.txt
Requires-Dist: boltons
Requires-Dist: docopt
Requires-Dist: portalocker
Provides-Extra: plugins
Requires-Dist: PuzzlePluginSystem>=0.8.0; extra == "plugins"
Provides-Extra: colors
Requires-Dist: colorama; extra == "colors"
Provides-Extra: testutils
Requires-Dist: pymta>=0.8; extra == "testutils"
Requires-Dist: schwarzlog; extra == "testutils"
Provides-Extra: testing
Requires-Dist: PuzzlePluginSystem>=0.8.0; extra == "testing"
Requires-Dist: pymta>=0.8; extra == "testing"
Requires-Dist: schwarzlog; extra == "testing"
Requires-Dist: dotmap; extra == "testing"
Requires-Dist: time-machine; implementation_name != "pypy" and extra == "testing"
Requires-Dist: pytest; extra == "testing"
Requires-Dist: setuptools; extra == "testing"
Requires-Dist: testfixtures; extra == "testing"
Dynamic: license-file
